gd_core_web_sm/__init__.py
gd_core_web_sm/config.cfg
gd_core_web_sm/meta.json
gd_core_web_sm/pos_aware_lemmatizer.py
gd_core_web_sm/setup.cfg
gd_core_web_sm/lookups/irregular_dict.json
gd_core_web_sm/models/Tags_Sheet.csv
gd_core_web_sm/models/__init__.py
gd_core_web_sm/models/best_tagging_model.pt
gd_core_web_sm/models/embedding_matrix.npy
gd_core_web_sm/models/tag_map.pkl
gd_core_web_sm/models/tagger_module.py
gd_core_web_sm/models/vocab.pkl
gd_core_web_sm/tokenizer/tokenizer.json
gd_core_web_sm-0.1.2.dist-info/licenses/LICENSE
gd_core_web_sm-0.1.2.dist-info/METADATA
gd_core_web_sm-0.1.2.dist-info/WHEEL
gd_core_web_sm-0.1.2.dist-info/entry_points.txt
gd_core_web_sm-0.1.2.dist-info/top_level.txt
gd_core_web_sm-0.1.2.dist-info/RECORD
