Metadata-Version: 2.4
Name: gd-core-web-sm
Version: 0.1.2
Summary: A spaCy-compatible Scottish Gaelic NLP pipeline with POS tagging and a POS-aware lemmatizer.
Author-email: Oskar Diyali <oskardiyali@cornellcollege.edu>
License-Expression: MIT
Project-URL: Homepage, https://github.com/CSRI-2024/lemmatizer_gaelic
Project-URL: Issues, https://github.com/CSRI-2024/lemmatizer_gaelic/issues
Classifier: Programming Language :: Python :: 3
Classifier: Topic :: Text Processing :: Linguistic
Requires-Python: >=3.8
License-File: LICENSE
Requires-Dist: spacy>=3.7.0
Requires-Dist: torch>=1.13.0
Dynamic: license-file
